{
    "version": "0.4.6",
    "url": "https://ghfast.top/https://github.com/Skardyy/mcat/releases/download/v0.4.6/mcat-x86_64-pc-windows-msvc.zip",
    "hash": "04233ab8c09c6df7fc02fb2c40b8e1ebd0eb3a5f4466f5446ffc07ad84c37c04",
    "license": "GPL-3.0-only",
    "bin": "mcat.exe",
    "homepage": "https://github.com/Skardyy/mcat",
    "description": "cat command for documents / images / videos and more!",
    "checkver": {
        "github": "https://github.com/Skardyy/mcat"
    },
    "autoupdate": {
        "url": "https://ghfast.top/https://github.com/Skardyy/mcat/releases/download/v$version/mcat-x86_64-pc-windows-msvc.zip",
        "hash": {
            "url": "https://github.com/Skardyy/mcat/releases/download/v$version/mcat-x86_64-pc-windows-msvc.zip.sha256"
        },
        "notes": [
            "Other available assets:",
            "https://ghfast.top/https://github.com/Skardyy/mcat/releases/download/v$version/source.tar.gz",
            "https://ghfast.top/https://github.com/Skardyy/mcat/archive/refs/tags/v$version.zip"
        ]
    },
    "notes": [
        "Other available assets:",
        "https://ghfast.top/https://github.com/Skardyy/mcat/releases/download/v0.4.6/source.tar.gz",
        "https://ghfast.top/https://github.com/Skardyy/mcat/archive/refs/tags/v0.4.6.zip"
    ]
}
