{
    "version": "0.10.4",
    "url": "https://github.store/wavetermdev/waveterm/releases/download/v0.10.4/Wave-win32-x64-0.10.4.msi",
    "hash": "eff0e2025264a4937ba90ece686b6956d248fca360f6e3ac575528cd482d8560",
    "license": "Apache-2.0",
    "shortcuts": [
        [
            "Wave.exe",
            "Wave"
        ]
    ],
    "extract_dir": "waveterm",
    "homepage": "https://github.com/wavetermdev/waveterm",
    "description": "An open-source, cross-platform terminal for seamless workflows",
    "checkver": {
        "github": "https://github.com/wavetermdev/waveterm"
    },
    "autoupdate": {
        "url": "https://github.store/wavetermdev/waveterm/releases/download/v$version/Wave-win32-x64-$version.msi",
        "hash": {
            "url": "$url.sha256"
        }
    }
}
